Workbook

Sheet Working Paper
A1: WORKING PAPER — Working Capital & Balance Sheet Movement
A2: Period: [กรอกงวด] Company: Consolidated (CONSO) Prepared by: ___________ Date: ___________
A3: # | B3: Account No. | C3: Account Name | D3: FS Caption | E3: Opening Balance (กรอกต้นงวด) | F3: Closing Balance (จาก TB) | G3: Change (Closing-Opening) | H3: CF Impact (ผลต่อ CF) | I3: CF Activity | J3: IC? | K3: Note / Reference
A4: 1. ลูกหนี้การค้า (Accounts Receivable)
A5: Logic: AR เพิ่ม = ใช้เงินสด = CF ลบ | AR ลด = เก็บเงินได้ = CF บวก | Activity: Operating
C6: Intercompany accounts highlighted in yellow
B7: 11121010 | C7: ลูกหนี้การค้า-กิจการที่ไม่เกี่ยวข้องกัน | D7: ลูกหนี้การค้า | F7: 21637.318 | G7: =F7-E7 | H7: =-G7 | I7: Operating
B8: 11121011 | C8: ลูกหนี้การค้า-ไฟแนนซ์ | D8: ลูกหนี้การค้า | F8: 31829.245 | G8: =F8-E8 | H8: =-G8 | I8: Operating
B9: 11121012 | C9: ลูกหนี้การค้า-ประกันภัย | D9: ลูกหนี้การค้า | F9: 149328.99 | G9: =F9-E9 | H9: =-G9 | I9: Operating
B10: 11121013 | C10: ลูกหนี้การค้า-รถเช่า | D10: ลูกหนี้การค้า | F10: 3953.1866 | G10: =F10-E10 | H10: =-G10 | I10: Operating
B11: 11121014 | C11: ลูกหนี้การค้า-คอเปอร์เรท | D11: ลูกหนี้การค้า | F11: 0 | G11: =F11-E11 | H11: =-G11 | I11: Operating
B12: 11121020 | C12: ลูกหนี้การค้า-ฮอนด้า ออโต้โมบิล | D12: ลูกหนี้การค้า | F12: 37301.63 | G12: =F12-E12 | H12: =-G12 | I12: Operating
B13: 11121099 | C13: ค่าเผื่อหนี้สงสัยจะสูญ | D13: ลูกหนี้การค้า | F13: -29536.03 | G13: =F13-E13 | H13: =-G13 | I13: Operating
C14: รวม 1. ลูกหนี้การค้า (Accounts Receivable) | E14: =SUM(E7:E13) | F14: =SUM(F7:F13) | G14: =SUM(G7:G13) | H14: =SUM(H7:H13) | I14: Operating
A16: 2. ลูกหนี้หมุนเวียนอื่น (Other Current Receivables)
A17: Logic: เพิ่ม = CF ลบ | Activity: Operating
C18: Intercompany accounts highlighted in yellow
B19: 11141010 | C19: ลูกหนี้เงินทดรอง-พนักงาน | D19: ลูกหนี้หมุนเวียนอื่น | F19: 2155.94 | G19: =F19-E19 | H19: =-G19 | I19: Operating
B20: 11151010 | C20: ลูกหนี้อื่น | D20: ลูกหนี้หมุนเวียนอื่น | F20: 7484.8206 | G20: =F20-E20 | H20: =-G20 | I20: Operating
B21: 11151035 | C21: ลูกหนี้เงิน-พนักงาน | D21: ลูกหนี้หมุนเวียนอื่น | F21: 46.1319 | G21: =F21-E21 | H21: =-G21 | I21: Operating
B22: 11151011 | C22: ค่าใช้จ่ายจ่ายล่วงหน้า | D22: ลูกหนี้หมุนเวียนอื่น | F22: 38542.029 | G22: =F22-E22 | H22: =-G22 | I22: Operating
B23: 11151015 | C23: ภาษีเงินได้ถูกหัก ณ ที่จ่าย | D23: สินทรัพย์ภาษีเงินได้ของงวดปัจจุบัน | F23: 6404.3739 | G23: =F23-E23 | H23: =-G23 | I23: Operating
B24: 11151017 | C24: รายได้ค้างรับ-ค่านายหน้าไฟแนนซ์ | D24: ลูกหนี้หมุนเวียนอื่น | F24: 1258.1504 | G24: =F24-E24 | H24: =-G24 | I24: Operating
B25: 11151018 | C25: รายได้ค้างรับ-ค่านายหน้าประกันภัย | D25: ลูกหนี้หมุนเวียนอื่น | F25: 3348.5612 | G25: =F25-E25 | H25: =-G25 | I25: Operating
B26: 11151019 | C26: รายได้ค้างรับ-ค่าแรงเคลมฮอนด้า | D26: ลูกหนี้หมุนเวียนอื่น | F26: 1835.9 | G26: =F26-E26 | H26: =-G26 | I26: Operating
B27: 11151020 | C27: รายได้ค้างรับ-อะไหล่เคลมฮอนด้า | D27: ลูกหนี้หมุนเวียนอื่น | F27: 16800.906 | G27: =F27-E27 | H27: =-G27 | I27: Operating
B28: 11151023 | C28: รายได้ค้างรับ-รางวัลการขาย | D28: ลูกหนี้หมุนเวียนอื่น | F28: 55906.995 | G28: =F28-E28 | H28: =-G28 | I28: Operating
B29: 11151028 | C29: รายได้ค้างรับ-ค่าแรงเคลม-คุณภาพ | D29: ลูกหนี้หมุนเวียนอื่น | F29: 3951.8503 | G29: =F29-E29 | H29: =-G29 | I29: Operating
B30: 11151029 | C30: รายได้ค้างรับ-ค่าแรงเคลม-Exclusive | D30: ลูกหนี้หมุนเวียนอื่น | F30: 2383.7 | G30: =F30-E30 | H30: =-G30 | I30: Operating
... B37: 11151012-1 | C37: ลูกหนี้กรมสรรพากร | D37: ลูกหนี้หมุนเวียนอื่น | F37: 48554.327 | G37: =F37-E37 | H37: =-G37 | I37: Operating
B38: 11121030 | C38: ลูกหนี้การค้า-กิจการที่เกี่ยวข้องกัน | D38: ลูกหนี้หมุนเวียนอื่น | F38: 0 | G38: =F38-E38 | H38: =-G38 | I38: Operating | J38: IC
B39: 11141020 | C39: ลูกหนี้เงินทดรอง-อื่น | D39: ลูกหนี้หมุนเวียนอื่น | F39: 1.1641532e-12 | G39: =F39-E39 | H39: =-G39 | I39: Operating
B40: 11141030 | C40: ลูกหนี้เงินทดรอง-กิจการที่เกี่ยวข้องกัน | D40: ลูกหนี้หมุนเวียนอื่น | F40: 0 | G40: =F40-E40 | H40: =-G40 | I40: Operating | J40: IC
B41: 11151021 | C41: เงินปันผลค้างรับ | D41: ลูกหนี้หมุนเวียนอื่น | F41: 0 | G41: =F41-E41 | H41: =-G41 | I41: Operating
B42: 11151024 | C42: contra ภาษีมูลค่าเพิ่ม | D42: ลูกหนี้หมุนเวียนอื่น | F42: 0 | G42: =F42-E42 | H42: =-G42 | I42: Operating
B43: 11151025 | C43: ลูกหนี้อื่น-กิจการที่เกี่ยวข้องกัน | D43: ลูกหนี้หมุนเวียนอื่น | F43: 0 | G43: =F43-E43 | H43: =-G43 | I43: Operating | J43: IC
B44: 11151026 | C44: รายได้ค้างรับบริการซ่อม | D44: ลูกหนี้หมุนเวียนอื่น | F44: 0 | G44: =F44-E44 | H44: =-G44 | I44: Operating
B45: 11212011 | C45: ดอกเบี้ยค้างรับจากบริษัทย่อย | D45: ลูกหนี้หมุนเวียนอื่น | F45: 0 | G45: =F45-E45 | H45: =-G45 | I45: Operating | J45: IC
B46: 11212031 | C46: ดอกเบี้ยค้างรับจากบริษัทอื่น | D46: ลูกหนี้หมุนเวียนอื่น | F46: 0 | G46: =F46-E46 | H46: =-G46 | I46: Operating
C47: รวม 2. ลูกหนี้หมุนเวียนอื่น (Other Current Receivables) | E47: =SUM(E19:E46) | F47: =SUM(F19:F46) | G47: =SUM(G19:G46) | H47: =SUM(H19:H46) | I47: Operating
A49: 3. ที่ดิน อาคาร อุปกรณ์ / PPE & Investment Property
A50: Logic: ดูร่วมกับรายการซื้อ/ขาย FA + ค่าเสื่อมที่ add-back ใน Operating | Activity: Investing
C51: Intercompany accounts highlighted in yellow
B52: 11221010 | C52: ที่ดิน | D52: ที่ดิน อาคารและอุปกรณ์ | F52: 2324088.3 | G52: =F52-E52 | H52: =-G52 | I52: Investing
B53: 11214010 | C53: อสังหาริมทรัพย์เพื่อการลงทุน | D53: อสังหาริมทรัพย์เพื่อการลงทุน | F53: 1662246.2 | G53: =F53-E53 | H53: =-G53 | I53: Investing
B54: 11221020 | C54: ส่วนปรับปรุงที่ดิน | D54: ที่ดิน อาคารและอุปกรณ์ | F54: 149023.14 | G54: =F54-E54 | H54: =-G54 | I54: Investing
B55: 11221030 | C55: อาคารและสิ่งปลูกสร้าง | D55: ที่ดิน อาคารและอุปกรณ์ | F55: 3545023.2 | G55: =F55-E55 | H55: =-G55 | I55: Investing
B56: 11221040 | C56: ส่วนปรับปรุงอาคาร | D56: ที่ดิน อาคารและอุปกรณ์ | F56: 1123287.3 | G56: =F56-E56 | H56: =-G56 | I56: Investing
B57: 11221050 | C57: เครื่องคอมพิวเตอร์ | D57: ที่ดิน อาคารและอุปกรณ์ | F57: 138512.29 | G57: =F57-E57 | H57: =-G57 | I57: Investing
B58: 11221060 | C58: เครื่องมือเครื่องใช้อุปกรณ์ช่าง | D58: ที่ดิน อาคารและอุปกรณ์ | F58: 904779.41 | G58: =F58-E58 | H58: =-G58 | I58: Investing
B59: 11221070 | C59: เครื่องตกแต่งและติดตั้งสำนักงาน | D59: ที่ดิน อาคารและอุปกรณ์ | F59: 282284.56 | G59: =F59-E59 | H59: =-G59 | I59: Investing
B60: 11221080 | C60: ยานพาหนะ | D60: ที่ดิน อาคารและอุปกรณ์ | F60: 369263.26 | G60: =F60-E60 | H60: =-G60 | I60: Investing
B61: 11221090 | C61: อุปกรณ์สำนักงาน | D61: ที่ดิน อาคารและอุปกรณ์ | F61: 76298.304 | G61: =F61-E61 | H61: =-G61 | I61: Investing
B62: 11221130 | C62: สินทรัพย์รอการจำหน่าย หรือ ทำลาย | D62: ที่ดิน อาคารและอุปกรณ์ | F62: 429.7125 | G62: =F62-E62 | H62: =-G62 | I62: Investing
B63: 11221100 | C63: งานระหว่างการก่อสร้าง | D63: ที่ดิน อาคารและอุปกรณ์ | F63: 12.3697 | G63: =F63-E63 | H63: =-G63 | I63: Investing
... B75: 11225010 | C75: ค่าเสื่อมราคาสะสมอสังหาริมทรัพย์เพื่อการลงทุน | D75: อสังหาริมทรัพย์เพื่อการลงทุน | F75: 0 | G75: =F75-E75 | H75: =-G75 | I75: Investing
C76: รวม 3. ที่ดิน อาคาร อุปกรณ์ / PPE & Investment Property | E76: =SUM(E52:E75) | F76: =SUM(F52:F75) | G76: =SUM(G52:G75) | H76: =SUM(H52:H75) | I76: Investing
A78: 4. สินทรัพย์สิทธิการใช้ ROU Asset (TFRS 16)
A79: Logic: Non-cash — ค่าเสื่อม ROU บวกกลับใน Operating | ชำระ Lease เงินต้น = Financing | Activity: Operating (add-back)
C80: Intercompany accounts highlighted in yellow
B81: 11231050 | C81: สินทรัพย์สิทธิการใช้ | D81: สินทรัพย์สิทธิการใช้ | F81: 2023109.7 | G81: =F81-E81 | H81: N/A — see note | I81: Operating (add-back)
B82: 11232050 | C82: ค่าเสื่อมราคาสะสม-สัญญาเช่า | D82: สินทรัพย์สิทธิการใช้ | F82: -641442.36 | G82: =F82-E82 | H82: N/A — see note | I82: Operating (add-back)
C83: รวม 4. สินทรัพย์สิทธิการใช้ ROU Asset (TFRS 16) | E83: =SUM(E81:E82) | F83: =SUM(F81:F82) | G83: =SUM(G81:G82) | H83: N/A | I83: Operating (add-back)
A85: 5. สินทรัพย์ภาษีเงินได้รอตัดบัญชี / สินทรัพย์อื่น
A86: Logic: เพิ่ม = CF ลบ | Activity: Investing
C87: Intercompany accounts highlighted in yellow
B88: 11231040 | C88: สินทรัพย์ภาษีเงินได้รอการตัดบัญชี | D88: สินทรัพย์ภาษีเงินได้รอการตัดบัญชี | F88: 170840.68 | G88: =F88-E88 | H88: =-G88 | I88: Investing
B89: 11212010 | C89: เงินให้กู้ยืมแก่บริษัทย่อย | D89: เงินให้กู้ยืมระยะยาวแก่บริษัทย่อย | F89: 0 | G89: =F89-E89 | H89: =-G89 | I89: Investing | J89: IC
B90: 11212030 | C90: เงินให้กู้ยืมแก่บริษัทอื่น | D90: เงินให้กู้ยืมระยะยาวแก่บริษัทย่อย | F90: 0 | G90: =F90-E90 | H90: =-G90 | I90: Investing
B91: 11213010 | C91: เงินลงทุนในบริษัทย่อย | D91: เงินลงทุนในบริษัทย่อย | F91: 0 | G91: =F91-E91 | H91: =-G91 | I91: Investing | J91: IC
B92: 21221012 | C92: หนี้สินภาษีเงินได้รอการตัดบัญชี | D92: สินทรัพย์ภาษีเงินได้รอการตัดบัญชี | F92: -15317.92 | G92: =F92-E92 | H92: =-G92 | I92: Investing
C93: รวม 5. สินทรัพย์ภาษีเงินได้รอตัดบัญชี / สินทรัพย์อื่น | E93: =SUM(E88:E92) | F93: =SUM(F88:F92) | G93: =SUM(G88:G92) | H93: =SUM(H88:H92) | I93: Investing
A95: 6. เจ้าหนี้การค้า (Accounts Payable)
A96: Logic: AP เพิ่ม = ยังไม่จ่าย = CF บวก | AP ลด = จ่ายแล้ว = CF ลบ | Activity: Operating
C97: Intercompany accounts highlighted in yellow
B98: 11113101 | C98: บัญชีพัก-ซื้อสินค้า | D98: เจ้าหนี้การค้า | F98: 13.1063 | G98: =F98-E98 | H98: =G98 | I98: Operating
B99: 21121010 | C99: เจ้าหนี้การค้า-กิจการที่ไม่เกี่ยวข้องกัน | D99: เจ้าหนี้การค้า | F99: -157708.24 | G99: =F99-E99 | H99: =G99 | I99: Operating
B100: 21121020 | C100: เจ้าหนี้การค้า-ฮอนด้า ออโต้โมบิล | D100: เจ้าหนี้การค้า | F100: -704632.27 | G100: =F100-E100 | H100: =G100 | I100: Operating
B101: 21121030-1 | C101: เจ้าหนี้การค้า-กิจการที่ไม่เกี่ยวข้องกัน-ของโป๊วะ | D101: เจ้าหนี้การค้า | F101: -36833.003 | G101: =F101-E101 | H101: =G101 | I101: Operating
B102: 21121040 | C102: ประมาณการส่วนลดอะไหล่/ส่งเสริมการขาย | D102: เจ้าหนี้การค้า | F102: 7929.0159 | G102: =F102-E102 | H102: =G102 | I102: Operating
B103: 21121050 | C103: เจ้าหนี้การค้า-ฝากขาย | D103: เจ้าหนี้การค้า | F103: 778.148 | G103: =F103-E103 | H103: =G103 | I103: Operating
B104: 21121030 | C104: เจ้าหนี้การค้า-กิจการที่เกี่ยวข้องกัน | D104: เจ้าหนี้การค้า | F104: 0 | G104: =F104-E104 | H104: =G104 | I104: Operating | J104: IC
C105: รวม 6. เจ้าหนี้การค้า (Accounts Payable) | E105: =SUM(E98:E104) | F105: =SUM(F98:F104) | G105: =SUM(G98:G104) | H105: =SUM(H98:H104) | I105: Operating
A107: 7. เจ้าหนี้หมุนเวียนอื่น / ค่าใช้จ่ายค้างจ่าย / ดอกเบี้ยค้างจ่าย
A108: Logic: เพิ่ม = CF บวก — รวม: ค่าใช้จ่ายค้างจ่าย, ดอกเบี้ยค้างจ่าย, เงินรับล่วงหน้า | Activity: Operating
C109: Intercompany accounts highlighted in yellow
B110: 21141011 | C110: ค่าใช้จ่ายค้างจ่าย | D110: เจ้าหนี้หมุนเวียนอื่น | F110: -58153.93 | G110: =F110-E110 | H110: =G110 | I110: Operating
B111: 21141012 | C111: เงินประกันสังคมค้างจ่าย | D111: เจ้าหนี้หมุนเวียนอื่น | F111: -6227 | G111: =F111-E111 | H111: =G111 | I111: Operating
B112: 21141014 | C112: เงินปันผลค้างจ่าย | D112: เจ้าหนี้หมุนเวียนอื่น | F112: -34.8929 | G112: =F112-E112 | H112: =G112 | I112: Operating
B113: 21141016 | C113: เงิน กยศ พนักงานค้างจ่าย | D113: เจ้าหนี้หมุนเวียนอื่น | F113: -757.87 | G113: =F113-E113 | H113: =G113 | I113: Operating
B114: 21142011 | C114: เงินรับล่วงหน้า-จองรถยนต์ | D114: เจ้าหนี้หมุนเวียนอื่น | F114: -6921.4858 | G114: =F114-E114 | H114: =G114 | I114: Operating
B115: 21142012 | C115: เงินรับล่วงหน้า-อะไหล่ | D115: เจ้าหนี้หมุนเวียนอื่น | F115: -43356.458 | G115: =F115-E115 | H115: =G115 | I115: Operating
B116: 21142013 | C116: เงินรับล่วงหน้า-Honda Pay Save | D116: เจ้าหนี้หมุนเวียนอื่น | F116: -15831.617 | G116: =F116-E116 | H116: =G116 | I116: Operating
B117: 21142014 | C117: เงินรับล่วงหน้า-ค่าทะเบียน | D117: เจ้าหนี้หมุนเวียนอื่น | F117: -2338.3124 | G117: =F117-E117 | H117: =G117 | I117: Operating
B118: 21142015 | C118: เงินรับล่วงหน้า-ค่าประกันภัย,พรบ. | D118: เจ้าหนี้หมุนเวียนอื่น | F118: -940.4203 | G118: =F118-E118 | H118: =G118 | I118: Operating
B119: 21142016 | C119: เงินมัดจำ-ป้ายแดง | D119: เจ้าหนี้หมุนเวียนอื่น | F119: -4370.7498 | G119: =F119-E119 | H119: =G119 | I119: Operating
B120: 21142019 | C120: เงินรับล่วงหน้า - ค่าแรงซ่อม | D120: เจ้าหนี้หมุนเวียนอื่น | F120: -341.9093 | G120: =F120-E120 | H120: =G120 | I120: Operating
B121: 21142020 | C121: เงินรับล่วงหน้า-เคลือบเซรามิค 9H | D121: เจ้าหนี้หมุนเวียนอื่น | F121: -29090 | G121: =F121-E121 | H121: =G121 | I121: Operating
... B131: 21151016 | C131: เงินประกันผลงาน - BP | D131: เจ้าหนี้หมุนเวียนอื่น | F131: -11576.946 | G131: =F131-E131 | H131: =G131 | I131: Operating
B132: 21122010 | C132: เจ้าหนี้-กิจการที่เกี่ยวข้องกัน | D132: เจ้าหนี้หมุนเวียนอื่น | F132: 0 | G132: =F132-E132 | H132: =G132 | I132: Operating | J132: IC
...

Sheet CF Summary (WC)
A1: สรุปผลกระทบ Working Capital ต่อ Cash Flow Statement (Indirect Method)
A2: รายการ | B2: CF Impact (บาท) | C2: Activity
A3: 1. ลูกหนี้การค้า (Accounts Receivable) | B3: ='Working Paper'!H14 | C3: Operating
A4: 2. ลูกหนี้หมุนเวียนอื่น (Other Current Receivables) | B4: ='Working Paper'!H47 | C4: Operating
A5: 3. ที่ดิน อาคาร อุปกรณ์ / PPE & Investment Property | B5: ='Working Paper'!H76 | C5: Investing
A6: 4. สินทรัพย์สิทธิการใช้ ROU Asset (TFRS 16) | B6: ดูรายละเอียด | C6: Operating (add-back)
A7: 5. สินทรัพย์ภาษีเงินได้รอตัดบัญชี / สินทรัพย์อื่น | B7: ='Working Paper'!H93 | C7: Investing
A8: 6. เจ้าหนี้การค้า (Accounts Payable) | B8: ='Working Paper'!H105 | C8: Operating
A9: 7. เจ้าหนี้หมุนเวียนอื่น / ค่าใช้จ่ายค้างจ่าย / ดอกเบี้ยค้างจ่าย | B9: ='Working Paper'!H147 | C9: Operating
A10: 8. หนี้สินตามสัญญาเช่า Lease Liability (TFRS 16) | B10: ดูรายละเอียด | C10: Financing
A11: 9. เงินกู้ยืมจากสถาบันการเงิน (Bank Loans) | B11: ='Working Paper'!H163 | C11: Financing
A12: 10. ประมาณการผลประโยชน์พนักงาน (Employee Benefit) | B12: ='Working Paper'!H170 | C12: Operating (add-back)
A13: 11. ภาษีเงินได้นิติบุคคลค้างจ่าย (Income Tax Payable) | B13: ='Working Paper'!H176 | C13: Operating
A14: 12. หนี้สินภาษีเงินได้รอตัดบัญชี / หนี้สินไม่หมุนเวียนอื่น | B14: ='Working Paper'!H183 | C14: Operating / Financing
A16: รวมผลกระทบ — Operating Activities | B16: =SUM(B3,B4,B6,B8,B9,B12,B13,B14)
A17: รวมผลกระทบ — Investing Activities | B17: =SUM(B5,B7)
A18: รวมผลกระทบ — Financing Activities | B18: =SUM(B10,B11)
A20: หมายเหตุ: ตัวเลขสีน้ำเงินใน Working Paper = กรอกเอง (Opening Balance) | สีเขียว = จาก TB | เซลล์สีเหลือง = Intercompany (IC) — ถูก Eliminate ใน CONSO

Sheet Instructions
A1: วิธีใช้ Working Paper Template นี้
A3: STEP 1 — กรอก Opening Balance (คอลัมน์ E สีน้ำเงิน)
A4: กรอกยอดยกมาต้นงวด (เช่น 31 Dec 2023) สำหรับทุก Account
A5: ถ้ามี TB งวดก่อนหน้า สามารถ paste ค่าตรงๆ ได้เลย
A7: STEP 2 — ตรวจสอบ Closing Balance (คอลัมน์ F สีเขียว)
A8: คอลัมน์ F ดึงมาจาก TB ที่ให้มา (CONSO) โดยอัตโนมัติ
A9: ถ้าตัวเลขไม่ตรงกับ TB ให้แจ้งทีม Accounting
A11: STEP 3 — ระบบคำนวณ Change และ CF Impact ให้อัตโนมัติ
A12: Change = Closing - Opening (คอลัมน์ G)
A13: CF Impact = Change * Sign (คอลัมน์ H) — ดูสูตรแต่ละ Section
A15: STEP 4 — ดูสรุปใน Sheet "CF Summary (WC)"
A16: Sheet นี้รวม CF Impact แยกตาม Operating / Investing / Financing
... A31: ให้ขอ TFRS 16 Schedule จากฝ่ายบัญชีเพิ่มเติม
